{
    "logs": [
        {
            "timestamp": "2026-03-03 14:14:19.281",
            "point_index": 0,
            "attempt_index": 0,
            "correct_direction": "E",
            "responded_direction": "NE",
            "status": "ongoing"
        },
        {
            "timestamp": "2026-03-03 14:14:25.392",
            "point_index": 0,
            "attempt_index": 1,
            "correct_direction": "SE",
            "responded_direction": "SE",
            "status": "ongoing"
        },
        {
            "timestamp": "2026-03-03 14:14:27.351",
            "point_index": 0,
            "attempt_index": 1,
            "correct_direction": "SE",
            "responded_direction": "N/A",
            "status": "success"
        },
        {
            "timestamp": "2026-03-03 14:14:31.669",
            "point_index": 1,
            "attempt_index": 0,
            "correct_direction": "NE",
            "responded_direction": "NE",
            "status": "ongoing"
        },
        {
            "timestamp": "2026-03-03 14:14:37.655",
            "point_index": 1,
            "attempt_index": 1,
            "correct_direction": "NE",
            "responded_direction": "NE",
            "status": "ongoing"
        },
        {
            "timestamp": "2026-03-03 14:14:43.002",
            "point_index": 1,
            "attempt_index": 2,
            "correct_direction": "NE",
            "responded_direction": "NE",
            "status": "ongoing"
        },
        {
            "timestamp": "2026-03-03 14:14:50.641",
            "point_index": 1,
            "attempt_index": 3,
            "correct_direction": "NE",
            "responded_direction": "N",
            "status": "ongoing"
        },
        {
            "timestamp": "2026-03-03 14:14:57.030",
            "point_index": 1,
            "attempt_index": 4,
            "correct_direction": "E",
            "responded_direction": "E",
            "status": "ongoing"
        },
        {
            "timestamp": "2026-03-03 14:14:58.779",
            "point_index": 1,
            "attempt_index": 4,
            "correct_direction": "E",
            "responded_direction": "N/A",
            "status": "success"
        },
        {
            "timestamp": "2026-03-03 14:15:03.668",
            "point_index": 2,
            "attempt_index": 0,
            "correct_direction": "N",
            "responded_direction": "NE",
            "status": "ongoing"
        },
        {
            "timestamp": "2026-03-03 14:15:09.570",
            "point_index": 2,
            "attempt_index": 1,
            "correct_direction": "NW",
            "responded_direction": "NW",
            "status": "ongoing"
        },
        {
            "timestamp": "2026-03-03 14:15:11.529",
            "point_index": 2,
            "attempt_index": 1,
            "correct_direction": "NW",
            "responded_direction": "N/A",
            "status": "success"
        },
        {
            "timestamp": "2026-03-03 14:15:16.237",
            "point_index": 3,
            "attempt_index": 0,
            "correct_direction": "NW",
            "responded_direction": "W",
            "status": "ongoing"
        },
        {
            "timestamp": "2026-03-03 14:15:21.875",
            "point_index": 3,
            "attempt_index": 1,
            "correct_direction": "NW",
            "responded_direction": "W",
            "status": "ongoing"
        },
        {
            "timestamp": "2026-03-03 14:15:28.653",
            "point_index": 3,
            "attempt_index": 2,
            "correct_direction": "N",
            "responded_direction": "W",
            "status": "ongoing"
        },
        {
            "timestamp": "2026-03-03 14:15:34.875",
            "point_index": 3,
            "attempt_index": 3,
            "correct_direction": "N",
            "responded_direction": "N",
            "status": "ongoing"
        },
        {
            "timestamp": "2026-03-03 14:15:40.416",
            "point_index": 3,
            "attempt_index": 4,
            "correct_direction": "N",
            "responded_direction": "N",
            "status": "ongoing"
        },
        {
            "timestamp": "2026-03-03 14:15:46.637",
            "point_index": 3,
            "attempt_index": 5,
            "correct_direction": "N",
            "responded_direction": "N",
            "status": "ongoing"
        },
        {
            "timestamp": "2026-03-03 14:15:48.374",
            "point_index": 3,
            "attempt_index": 5,
            "correct_direction": "N",
            "responded_direction": "N/A",
            "status": "success"
        },
        {
            "timestamp": "2026-03-03 14:15:52.305",
            "point_index": 4,
            "attempt_index": 0,
            "correct_direction": "SW",
            "responded_direction": "SW",
            "status": "ongoing"
        },
        {
            "timestamp": "2026-03-03 14:15:54.263",
            "point_index": 4,
            "attempt_index": 0,
            "correct_direction": "SW",
            "responded_direction": "N/A",
            "status": "success"
        },
        {
            "timestamp": "2026-03-03 14:15:58.359",
            "point_index": 5,
            "attempt_index": 0,
            "correct_direction": "SW",
            "responded_direction": "SW",
            "status": "ongoing"
        },
        {
            "timestamp": "2026-03-03 14:16:04.443",
            "point_index": 5,
            "attempt_index": 1,
            "correct_direction": "SW",
            "responded_direction": "S",
            "status": "ongoing"
        },
        {
            "timestamp": "2026-03-03 14:16:09.776",
            "point_index": 5,
            "attempt_index": 2,
            "correct_direction": "SW",
            "responded_direction": "SW",
            "status": "ongoing"
        },
        {
            "timestamp": "2026-03-03 14:16:17.026",
            "point_index": 5,
            "attempt_index": 3,
            "correct_direction": "W",
            "responded_direction": "SW",
            "status": "ongoing"
        },
        {
            "timestamp": "2026-03-03 14:16:23.150",
            "point_index": 5,
            "attempt_index": 4,
            "correct_direction": "N",
            "responded_direction": "W",
            "status": "ongoing"
        },
        {
            "timestamp": "2026-03-03 14:16:30.821",
            "point_index": 5,
            "attempt_index": 5,
            "correct_direction": "NE",
            "responded_direction": "N",
            "status": "ongoing"
        },
        {
            "timestamp": "2026-03-03 14:16:36.899",
            "point_index": 5,
            "attempt_index": 6,
            "correct_direction": "E",
            "responded_direction": "NE",
            "status": "ongoing"
        },
        {
            "timestamp": "2026-03-03 14:16:42.900",
            "point_index": 5,
            "attempt_index": 7,
            "correct_direction": "S",
            "responded_direction": "S",
            "status": "ongoing"
        },
        {
            "timestamp": "2026-03-03 14:16:44.650",
            "point_index": 5,
            "attempt_index": 7,
            "correct_direction": "S",
            "responded_direction": "N/A",
            "status": "success"
        },
        {
            "timestamp": "2026-03-03 14:16:48.706",
            "point_index": 6,
            "attempt_index": 0,
            "correct_direction": "S",
            "responded_direction": "S",
            "status": "ongoing"
        },
        {
            "timestamp": "2026-03-03 14:16:54.566",
            "point_index": 6,
            "attempt_index": 1,
            "correct_direction": "S",
            "responded_direction": "SE",
            "status": "ongoing"
        },
        {
            "timestamp": "2026-03-03 14:17:01.913",
            "point_index": 6,
            "attempt_index": 2,
            "correct_direction": "W",
            "responded_direction": "W",
            "status": "ongoing"
        },
        {
            "timestamp": "2026-03-03 14:17:03.663",
            "point_index": 6,
            "attempt_index": 2,
            "correct_direction": "W",
            "responded_direction": "N/A",
            "status": "success"
        },
        {
            "timestamp": "2026-03-03 14:17:08.496",
            "point_index": 7,
            "attempt_index": 0,
            "correct_direction": "W",
            "responded_direction": "S",
            "status": "ongoing"
        },
        {
            "timestamp": "2026-03-03 14:17:13.968",
            "point_index": 7,
            "attempt_index": 1,
            "correct_direction": "NW",
            "responded_direction": "SW",
            "status": "ongoing"
        },
        {
            "timestamp": "2026-03-03 14:17:20.565",
            "point_index": 7,
            "attempt_index": 2,
            "correct_direction": "N",
            "responded_direction": "N",
            "status": "ongoing"
        },
        {
            "timestamp": "2026-03-03 14:17:25.648",
            "point_index": 7,
            "attempt_index": 3,
            "correct_direction": "N",
            "responded_direction": "N",
            "status": "ongoing"
        },
        {
            "timestamp": "2026-03-03 14:17:27.398",
            "point_index": 7,
            "attempt_index": 3,
            "correct_direction": "N",
            "responded_direction": "N/A",
            "status": "success"
        },
        {
            "timestamp": "2026-03-03 14:17:31.856",
            "point_index": 8,
            "attempt_index": 0,
            "correct_direction": "SE",
            "responded_direction": "E",
            "status": "ongoing"
        },
        {
            "timestamp": "2026-03-03 14:17:37.912",
            "point_index": 8,
            "attempt_index": 1,
            "correct_direction": "S",
            "responded_direction": "S",
            "status": "ongoing"
        },
        {
            "timestamp": "2026-03-03 14:17:39.661",
            "point_index": 8,
            "attempt_index": 1,
            "correct_direction": "S",
            "responded_direction": "N/A",
            "status": "success"
        },
        {
            "timestamp": "2026-03-03 14:17:45.467",
            "point_index": 9,
            "attempt_index": 0,
            "correct_direction": "NE",
            "responded_direction": "NE",
            "status": "ongoing"
        },
        {
            "timestamp": "2026-03-03 14:17:51.077",
            "point_index": 9,
            "attempt_index": 1,
            "correct_direction": "NE",
            "responded_direction": "E",
            "status": "ongoing"
        },
        {
            "timestamp": "2026-03-03 14:17:56.355",
            "point_index": 9,
            "attempt_index": 2,
            "correct_direction": "N",
            "responded_direction": "N",
            "status": "ongoing"
        },
        {
            "timestamp": "2026-03-03 14:17:58.105",
            "point_index": 9,
            "attempt_index": 2,
            "correct_direction": "N",
            "responded_direction": "N/A",
            "status": "success"
        }
    ]
}