{
    "logs": [
        {
            "timestamp": "2026-03-05 12:38:28.868",
            "point_index": 0,
            "attempt_index": 0,
            "correct_direction": "N",
            "responded_direction": "NE",
            "status": "ongoing"
        },
        {
            "timestamp": "2026-03-05 12:38:34.547",
            "point_index": 0,
            "attempt_index": 1,
            "correct_direction": "W",
            "responded_direction": "W",
            "status": "ongoing"
        },
        {
            "timestamp": "2026-03-05 12:38:36.284",
            "point_index": 0,
            "attempt_index": 1,
            "correct_direction": "W",
            "responded_direction": "N/A",
            "status": "success"
        },
        {
            "timestamp": "2026-03-05 12:38:40.575",
            "point_index": 1,
            "attempt_index": 0,
            "correct_direction": "N",
            "responded_direction": "NE",
            "status": "ongoing"
        },
        {
            "timestamp": "2026-03-05 12:38:47.199",
            "point_index": 1,
            "attempt_index": 1,
            "correct_direction": "NW",
            "responded_direction": "N",
            "status": "ongoing"
        },
        {
            "timestamp": "2026-03-05 12:38:52.852",
            "point_index": 1,
            "attempt_index": 2,
            "correct_direction": "W",
            "responded_direction": "W",
            "status": "ongoing"
        },
        {
            "timestamp": "2026-03-05 12:38:54.602",
            "point_index": 1,
            "attempt_index": 2,
            "correct_direction": "W",
            "responded_direction": "N/A",
            "status": "success"
        },
        {
            "timestamp": "2026-03-05 12:39:00.060",
            "point_index": 2,
            "attempt_index": 0,
            "correct_direction": "NE",
            "responded_direction": "E",
            "status": "ongoing"
        },
        {
            "timestamp": "2026-03-05 12:39:05.977",
            "point_index": 2,
            "attempt_index": 1,
            "correct_direction": "NE",
            "responded_direction": "E",
            "status": "ongoing"
        },
        {
            "timestamp": "2026-03-05 12:39:12.602",
            "point_index": 2,
            "attempt_index": 2,
            "correct_direction": "NE",
            "responded_direction": "E",
            "status": "ongoing"
        },
        {
            "timestamp": "2026-03-05 12:39:18.392",
            "point_index": 2,
            "attempt_index": 3,
            "correct_direction": "N",
            "responded_direction": "NE",
            "status": "ongoing"
        },
        {
            "timestamp": "2026-03-05 12:39:24.032",
            "point_index": 2,
            "attempt_index": 4,
            "correct_direction": "N",
            "responded_direction": "NE",
            "status": "ongoing"
        },
        {
            "timestamp": "2026-03-05 12:39:29.906",
            "point_index": 2,
            "attempt_index": 5,
            "correct_direction": "NW",
            "responded_direction": "NE",
            "status": "ongoing"
        },
        {
            "timestamp": "2026-03-05 12:39:36.892",
            "point_index": 2,
            "attempt_index": 6,
            "correct_direction": "NW",
            "responded_direction": "NE",
            "status": "ongoing"
        },
        {
            "timestamp": "2026-03-05 12:39:42.989",
            "point_index": 2,
            "attempt_index": 7,
            "correct_direction": "W",
            "responded_direction": "W",
            "status": "ongoing"
        },
        {
            "timestamp": "2026-03-05 12:39:48.836",
            "point_index": 2,
            "attempt_index": 8,
            "correct_direction": "W",
            "responded_direction": "W",
            "status": "ongoing"
        },
        {
            "timestamp": "2026-03-05 12:39:55.016",
            "point_index": 2,
            "attempt_index": 9,
            "correct_direction": "W",
            "responded_direction": "W",
            "status": "ongoing"
        },
        {
            "timestamp": "2026-03-05 12:39:56.752",
            "point_index": 2,
            "attempt_index": 9,
            "correct_direction": "W",
            "responded_direction": "N/A",
            "status": "success"
        },
        {
            "timestamp": "2026-03-05 12:40:02.752",
            "point_index": 3,
            "attempt_index": 0,
            "correct_direction": "E",
            "responded_direction": "E",
            "status": "ongoing"
        },
        {
            "timestamp": "2026-03-05 12:40:08.488",
            "point_index": 3,
            "attempt_index": 1,
            "correct_direction": "E",
            "responded_direction": "E",
            "status": "ongoing"
        },
        {
            "timestamp": "2026-03-05 12:40:14.238",
            "point_index": 3,
            "attempt_index": 2,
            "correct_direction": "E",
            "responded_direction": "E",
            "status": "ongoing"
        },
        {
            "timestamp": "2026-03-05 12:40:15.988",
            "point_index": 3,
            "attempt_index": 2,
            "correct_direction": "E",
            "responded_direction": "N/A",
            "status": "success"
        },
        {
            "timestamp": "2026-03-05 12:40:24.196",
            "point_index": 4,
            "attempt_index": 0,
            "correct_direction": "SE",
            "responded_direction": "SE",
            "status": "ongoing"
        },
        {
            "timestamp": "2026-03-05 12:40:29.946",
            "point_index": 4,
            "attempt_index": 1,
            "correct_direction": "SE",
            "responded_direction": "SE",
            "status": "ongoing"
        },
        {
            "timestamp": "2026-03-05 12:40:36.626",
            "point_index": 4,
            "attempt_index": 2,
            "correct_direction": "SE",
            "responded_direction": "SE",
            "status": "ongoing"
        },
        {
            "timestamp": "2026-03-05 12:40:38.584",
            "point_index": 4,
            "attempt_index": 2,
            "correct_direction": "SE",
            "responded_direction": "N/A",
            "status": "success"
        },
        {
            "timestamp": "2026-03-05 12:40:43.042",
            "point_index": 5,
            "attempt_index": 0,
            "correct_direction": "S",
            "responded_direction": "SW",
            "status": "ongoing"
        },
        {
            "timestamp": "2026-03-05 12:40:49.500",
            "point_index": 5,
            "attempt_index": 1,
            "correct_direction": "SE",
            "responded_direction": "SE",
            "status": "ongoing"
        },
        {
            "timestamp": "2026-03-05 12:40:51.459",
            "point_index": 5,
            "attempt_index": 1,
            "correct_direction": "SE",
            "responded_direction": "N/A",
            "status": "success"
        },
        {
            "timestamp": "2026-03-05 12:40:55.763",
            "point_index": 6,
            "attempt_index": 0,
            "correct_direction": "SW",
            "responded_direction": "SW",
            "status": "ongoing"
        },
        {
            "timestamp": "2026-03-05 12:41:03.249",
            "point_index": 6,
            "attempt_index": 1,
            "correct_direction": "SW",
            "responded_direction": "SW",
            "status": "ongoing"
        },
        {
            "timestamp": "2026-03-05 12:41:05.208",
            "point_index": 6,
            "attempt_index": 1,
            "correct_direction": "SW",
            "responded_direction": "N/A",
            "status": "success"
        },
        {
            "timestamp": "2026-03-05 12:41:09.999",
            "point_index": 7,
            "attempt_index": 0,
            "correct_direction": "W",
            "responded_direction": "W",
            "status": "ongoing"
        },
        {
            "timestamp": "2026-03-05 12:41:15.958",
            "point_index": 7,
            "attempt_index": 1,
            "correct_direction": "W",
            "responded_direction": "W",
            "status": "ongoing"
        },
        {
            "timestamp": "2026-03-05 12:41:17.708",
            "point_index": 7,
            "attempt_index": 1,
            "correct_direction": "W",
            "responded_direction": "N/A",
            "status": "success"
        },
        {
            "timestamp": "2026-03-05 12:41:25.582",
            "point_index": 8,
            "attempt_index": 0,
            "correct_direction": "NW",
            "responded_direction": "N",
            "status": "ongoing"
        },
        {
            "timestamp": "2026-03-05 12:41:31.664",
            "point_index": 8,
            "attempt_index": 1,
            "correct_direction": "W",
            "responded_direction": "W",
            "status": "ongoing"
        },
        {
            "timestamp": "2026-03-05 12:41:33.416",
            "point_index": 8,
            "attempt_index": 1,
            "correct_direction": "W",
            "responded_direction": "N/A",
            "status": "success"
        },
        {
            "timestamp": "2026-03-05 12:41:37.929",
            "point_index": 9,
            "attempt_index": 0,
            "correct_direction": "NW",
            "responded_direction": "NE",
            "status": "ongoing"
        },
        {
            "timestamp": "2026-03-05 12:41:43.998",
            "point_index": 9,
            "attempt_index": 1,
            "correct_direction": "W",
            "responded_direction": "W",
            "status": "ongoing"
        },
        {
            "timestamp": "2026-03-05 12:41:51.748",
            "point_index": 9,
            "attempt_index": 2,
            "correct_direction": "W",
            "responded_direction": "W",
            "status": "ongoing"
        },
        {
            "timestamp": "2026-03-05 12:41:53.497",
            "point_index": 9,
            "attempt_index": 2,
            "correct_direction": "W",
            "responded_direction": "N/A",
            "status": "success"
        }
    ]
}